networkx_algo_common_subtree/balanced_embedding.py
networkx_algo_common_subtree/tree_embedding.py
networkx_algo_common_subtree/balanced_isomorphism.py
networkx_algo_common_subtree/balanced_isomorphism_cython.cpython-39-x86_64-linux-gnu.so
networkx_algo_common_subtree/balanced_embedding_cython.cpython-39-x86_64-linux-gnu.so
networkx_algo_common_subtree/tree_isomorphism.py
networkx_algo_common_subtree/balanced_sequence.py
networkx_algo_common_subtree/utils.py
networkx_algo_common_subtree/__init__.py
networkx_algo_common_subtree/_types.py
networkx_algo_common_subtree-0.2.2.dist-info/WHEEL
networkx_algo_common_subtree-0.2.2.dist-info/RECORD
networkx_algo_common_subtree-0.2.2.dist-info/top_level.txt
networkx_algo_common_subtree-0.2.2.dist-info/METADATA
